quick_gr/__init__.py
quick_gr/help.py
quick_gr/command/__init__.py
quick_gr/command/make.py
quick_gr/command/normal_command.py
quick_gr-0.1.8.dist-info/METADATA
quick_gr-0.1.8.dist-info/WHEEL
quick_gr-0.1.8.dist-info/entry_points.txt
quick_gr-0.1.8.dist-info/top_level.txt
quick_gr-0.1.8.dist-info/RECORD
